README.rst
setup.py
accelpy/__init__.py
accelpy/__main__.py
accelpy/accel.py
accelpy/command.py
accelpy/compile.py
accelpy/const.py
accelpy/cpp.py
accelpy/cudahip.py
accelpy/fortran.py
accelpy/kernel.py
accelpy/util.py
accelpy.egg-info/PKG-INFO
accelpy.egg-info/SOURCES.txt
accelpy.egg-info/dependency_links.txt
accelpy.egg-info/entry_points.txt
accelpy.egg-info/requires.txt
accelpy.egg-info/top_level.txt