Metadata-Version: 1.2
Name: accelpy
Version: 0.6.18
Summary: Scalable Accelerator Interface in Python
Home-page: UNKNOWN
Author: Youngsung Kim
Author-email: youngsung.kim.act2@gmail.com
License: UNKNOWN
Project-URL: Bug Reports, https://github.com/grnydawn/accelpy/issues
Project-URL: Source, https://github.com/grnydawn/accelpy
Keywords: GPU,CPU,Accelerator,Cuda,Hip,OpenAcc,OpenMP,Numpy,C++,Fortran,accelpy
Platform: UNKNOWN
Classifier: Development Status :: 3 - Alpha
Classifier: Intended Audience :: Science/Research
Classifier: Topic :: Scientific/Engineering
Classifier: License :: OSI Approved :: MIT License
Classifier: Programming Language :: Python :: 3
Classifier: Programming Language :: Python :: 3.5
Classifier: Programming Language :: Python :: 3.6
Classifier: Programming Language :: Python :: 3.7
Classifier: Programming Language :: Python :: 3.8
